{
    "title": "tạm giữ hình_sự nam thanh_niên ' dụ_dỗ ' bé gái 12 tuổi làm chuyện vợ_chồng",
    "abstract": "thấy bé h. mới 12 tuổi nhưng đã phổng_phao như thiếu_nữ , trung đã nhiều lần dụ_dỗ làm chuyện vợ_chồng .",
    "article": [
        "ngày 26/3 , thông_tin từ công_an huyện định_quán , tỉnh đồng_nai cho biết , cơ_quan này đang tạm giữ hình_sự đối_tượng đỗ_minh_trung ( 25 tuổi , ngụ huyện định_quán ) để điều_tra về hành_vi hiếp_dâm người dưới 16 tuổi .",
        "nạn_nhân bị hiếp_dâm là cháu đ. t.t . h .",
        "( sn 2006 , ngụ huyện định_quán ) .",
        "theo thông_tin , trước đó , ngày 20/3 , bà m.t . n .",
        "( mẹ ruột em h. ) dẫn theo con là cháu h. đến cơ_quan công_an để tố_cáo về việc con_gái bà bị một thanh_niên quen_biết hiếp_dâm .",
        "cụ_thể , theo trình_báo của bà n. , cháu h. có quen_biết với trung và nhiều lần bị trung dở trò đồi_bại .",
        "bà n. có hỏi thì cháu h. cho_biết từ khoảng tháng 2 đến tháng 3 này , trung đã nhiều lần dụ_dỗ bé h. làm chuyện người_lớn .",
        "khi thấy con_gái có dấu_hiệu bất_thường về tâm_sinh_lý , bà n. đã gặng hỏi thì cháu h. mới kể toàn_bộ sự_việc .",
        "ngay sau đó , bà n. đã đến cơ_quan công_an tố_cáo hành_vi của trung .",
        "khi được mời lên làm_việc , trung đã nhanh_chóng cúi đầu thừa_nhận hành_vi phạm_tội .",
        "hiện vụ_việc đang được cơ_quan công_an tiếp_tục điều_tra , làm rõ ."
    ],
    "image": [
        "trung nhiều lần làm chuyện người_lớn với h. ( ảnh minh_hoạ )"
    ],
    "label": [
        6,
        7,
        0
    ]
}