{
    "title": "điều_tra vụ cô gái bị giật tóc , đánh sưng mặt vì quay xe_buýt “ đánh võng ”",
    "abstract": "khiếp sợ khi tài xế xe buýt chạy với tốc độ cao , lạng lách đánh võng , cô gái xin xuống xe và dùng điện thoại chụp ảnh thì bị giật tóc , đánh sưng mặt .",
    "article": [
        "trưa 12/3 , thông_tin từ công_an huyện cẩm xuyên , tỉnh hà tĩnh , đơn vị đang tiến hành xác minh , điều tra theo phản ánh của chị võ_thị_hoài ( sn 1992 , trú xã cẩm_minh , huyện cẩm xuyên ) về việc bị tài_xế và phụ xe_buýt đánh chảy máu mũi khi cầm điện_thoại chụp hình xe_buýt lạng_lách , đánh_võng .",
        "theo chị võ thị hoài , vào chiều 11/3 , chị võ_thị_hoài lên xe_buýt mang bks 38 b -011.16 ( chưa rõ danh_tính tài_xế ) từ tp. hà_tĩnh về xã cẩm_minh .",
        "thời điểm này , tài_xế điều khiển xe chạy với tốc_độ nhanh , lạng_lách đánh_võng nên khiến chị hoài và nhiều hành_khách trên xe hoảng_sợ .",
        "nhiều hàng khách trên xe lên tiếng nhắc nhở nhưng tài xế “ bỏ ngoài tai ” .",
        "do quá lo sợ , nên dù chưa đến điểm đến nhưng khi xe đi đến thị_trấn cẩm_xuyên , chị hoài đã xin xuống xe .",
        "sau khi xuống , chị cầm điện_thoại lên chụp biển số xe_buýt để phản_ánh với cơ_quan chức năng .",
        "bất ngờ , tài_xế và phụ xe lao xuống , túm tóc chị hoài , đánh liên tiếp vào phần mặt rồi sau đó tiếp tục lên xe_buýt di chuyển .",
        "“ quá trình xe chạy lạng lách , đánh võng đã khiến rất nhiều hành khách sợ hãi .",
        "tôi nghĩ , đây là xe buýt của công_ty nên khi xuống tôi đã chụp lại biển số để phản ánh , nhằm bảo vệ tính mạng cho những hành khách khác sau này .",
        "thế nhưng , phát hiện tôi chụp ảnh , trên xe có 2 người 1 nam và 1 nữ nhảy xuống , giật tóc và đòi lấy điện thoại của tôi .",
        "2 người này còn liên tiếp đánh vào mặt tôi và nói ai cho phép mày chụp ảnh .",
        "có một số người trên xe chạy xuống can_ngăn , 1 số người dân chứng kiến đã quay lại clip đánh sau đó chở tôi đến cơ_quan công_an trình báo ” , chị hoài kể lại .",
        "theo chị hoài , điều khiến chị buồn nhất đó là thời điểm xảy ra sự việc , rất nhiều người chứng kiến đã phẫn nộ chạy vào can_ngăn nhưng trước sự hung hãn của tài xế xe buýt , họ cũng sợ nên sau đó chỉ dám đứng theo_dõi , mặc chị bị đánh .",
        "hiện , vụ việc đang được điều tra , làm rõ ."
    ],
    "image": [
        "chị hoài bị đánh sưng mặt vì quay , chụp lại chiếc xe buýt"
    ],
    "label": [
        9,
        7
    ]
}