{
    "title": "bị bắt vì mua bán thuốc nổ kiếm lời",
    "abstract": "tại cơ_quan công_an , ông hà khai có người tìm đến nhà muốn mua thuốc nổ nên ông đi mua 10kg về với ý định bán lại để kiếm lời .",
    "article": [
        "trưa 7-5 , công_an huyện cư m ' gar ( đắk lắk ) cho_biết đã bàn giao ông nguyễn_văn_hà ( 57 tuổi ) trú tại xã ea_kpam , huyện cư_m ' gar cho phòng an_ninh điều tra công_an tỉnh này để thụ lý điều tra theo thẩm quyền về hành vi mua bán , tàng trữ trái phép vật liệu nổ được quy định tại điều 305 bộ luật hình sự .",
        "trước đó , khoảng 10h30 ngày 6-5 , sau một thời gian theo dõi , một tổ công_tác của đội cảnh_sát quản_lý hành_chính về trật_tự xã_hội công_an huyện cư m ' gar đã tiến hành kiểm tra nhà ông hà ở thôn 8 , xã ea_kpam và phát hiện ông này đang tàng_trữ trái_phép 10kg thuốc_nổ .",
        "công_an đã bắt khẩn cấp ông hà và tịch thu 10kg thuốc nổ để phục vụ công tác điều tra .",
        "tại cơ_quan công_an , bước_đầu ông hà khai nhận cách đây khoảng 1 tuần có một nam thanh_niên ( không rõ nhân_thân ) đến nhà ông đặt vấn_đề mua 10kg thuốc_nổ để về đào giếng .",
        "lúc này ông hà đồng_ý và thoả_thuận giá là 850.000 đồng / kg .",
        "đến sáng 6-5 , ông hà lên tp buôn_ma_thuột tìm gặp một người tên trung để mua 10kg thuốc_nổ với giá 750.000 / kg .",
        "tuy_nhiên , khi vừa mang về đến nhà , trong lúc đang điện thoại liên hệ khách đến lấy thuốc nổ thì ông hà bị công_an huyện cư m ' gar ập vào kiểm tra bắt quả tang …",
        "theo công_an huyện cư_m ’ gar , ông hà là người chuyên mua thuốc nổ về bán lại cho người sử dụng đào giếng để kiếm lời .",
        "đây là hành vi rất nguy hiểm cho chính gia đình ông hà cũng như những người khác khi tàng trữ lượng lớn chất nổ trong nhà ."
    ],
    "image": [
        "ông nguyễn văn_hà - ảnh : c.a ."
    ],
    "label": [
        7,
        3,
        5
    ]
}