{
    "title": "diệt kiến đâu cần xài thuốc !",
    "abstract": "kiến là những vị ' khách không mời ' khó_chịu nhất mà nhà nào cũng gặp phải . có cách nào diệt chúng hiệu_quả mà an_toàn ?",
    "article": [
        "dưới đây là vài mẹo nhỏ do trang wikihow tổng_hợp và giới_thiệu :",
        "nước rửa chén : rót 1 phần nước rửa chén và 2 phần nước vào trong chai , lắc kỹ để dung_dịch hoà_tan hoàn_toàn .",
        "khi thấy kiến , hãy xịt hỗn_hợp lên chúng .",
        "lũ kiến sẽ chựng lại và bị ngạt .",
        "dùng giẻ ướt lau sạch xác_kiến và giữ chai xịt đó để cho dành cho lần sau .",
        "ngoài kiến , bạn cũng có_thể dùng nước rửa chén để diệt gián .",
        "giấm trắng : giấm là một chất làm sạch tuyệt_vời trong nhà , khi khô đi cũng không để lại mùi .",
        "để diệt kiến , bạn có_thể hoà giấm và nước với lượng bằng nhau vào trong một chai xịt .",
        "xịt trực_tiếp lên kiến để giết chúng , sau đó dùng khăn ướt lau sạch và vứt bỏ .",
        "bạn cũng có_thể dùng giấm và nước xịt quanh bậu cửa_sổ , lối ra vào ... để ngăn_kiến vào nhà .",
        "nước_cốt chanh : nếu không chịu được mùi giấm , bạn có_thể xịt kiến bằng dung_dịch nước cốt chanh .",
        "cách làm rất đơn_giản : hoà 1 phần nước_cốt chanh với 3 phần nước rồi xịt kiến .",
        "lũ kiến rất ghét chất axit citric có trong nước cốt chanh , do đó bạn có_thể xịt dung_dịch này xung_quanh nhà để ngăn_chặn chúng bò vào ."
    ],
    "image": [
        "pha giấm và nước làm ' thuốc ' xịt kiến - ảnh minh_hoạ : hunker"
    ],
    "label": [
        6,
        12
    ]
}