{
    "title": "cụ ông 85 tuổi tay_không đánh_đuổi cướp có vũ_trang ở ireland",
    "abstract": "dù bị đe_doạ bằng búa và súng , nhưng ông lão không hề nao_núng mà xông vào túm cổ , ngáng chân khiến lũ cướp bỏ chạy .",
    "article": [
        "cụ o ' connor chống trả lũ cướp .",
        "denis o ' connor , 85 tuổi , đang ngồi trong văn_phòng của bar_one_racing - trung_tâm cá_cược thể_thao tại glanmire , hạt cork , ireland hôm 15/9 , thì ba tên cướp đeo mặt_nạ , cầm búa và súng xông vào , theo bbc .",
        "hai tên hướng về phía quầy thu_ngân , đe_doạ quản_lý tim_murphy mở két lấy tiền .",
        "tên thứ ba chĩa súng vào o ' connor nhưng ông lão đầu bạc trắng không hề nao_núng .",
        "ông đi vào quầy thu_ngân , túm cổ tên cướp mặc đồ trắng khiến hắn bỏ chạy về phía cửa .",
        "o ' connor đuổi theo nhưng hắn chạy thoát cùng tên cầm súng .",
        "ông lão tiếp_tục quay lại giúp_đỡ tim_murphy .",
        "khi tên cuối_cùng bỏ chạy khỏi quầy thu_ngân , o ' connor nghiêng người , gạt tay lên đầu tên cướp và giơ chân ngáng đường khiến hắn ngã nhào ra đất .",
        "ông tiếp_tục đá cho đến khi tên này bỏ chạy .",
        "toàn_bộ sự_việc diễn ra trong 30 giây .",
        "video đang được chia_sẻ hàng trăm_nghìn lần trên internet .",
        "tim murphy cho_hay anh cảm_thấy vô_cùng biết_ơn ông cụ đã giúp_đỡ đánh_đuổi bọn cướp .",
        "ông o ' connor từ_chối mọi đề_nghị phỏng_vấn .",
        "sáng 17/9 , ông cụ vẫn ra sân_chơi trò bóng lỗ như thường_lệ .",
        "cảnh_sát ireland hôm_qua phát_hành video kêu_gọi người_dân thông_báo nếu phát_hiện kẻ tình_nghi .",
        "họ cũng khuyên người_dân chớ chống_cự nếu gặp cướp ."
    ],
    "image": [
        "cụ o ' connor chống trả lũ cướp .",
        "video : bbc ."
    ],
    "label": [
        4,
        3,
        1
    ]
}