{
    "title": "trump : ' tôi rất thích tổng_thống obama '",
    "abstract": "donald_trump cho_biết ông rất thích tổng_thống barack_obama sau khi hai người gặp nhau tại nhà_trắng .",
    "article": [
        "tổng_thống đắc_cử donald_trump và tổng_thống barack_obama phát_biểu với báo_giới sau cuộc gặp tại nhà_trắng hôm 10/11 .",
        "\" tôi không biết mình có thích ông ấy không .",
        "tôi nghĩ là không nhưng thực_ra là có .",
        "tôi rất thích ông ấy \" , tổng_thống mỹ đắc_cử donald_trump cho_biết trong cuộc phỏng_vấn với new_york_times ngày 22/11 .",
        "trump , lúc tranh_cử , từng doạ sẽ đảo_ngược nhiều sáng_kiến mà tổng_thống barack_obama bảo_vệ .",
        "ông gọi ông obama là nhà_lãnh_đạo thất_bại , không phù_hợp làm tổng_thống suốt nhiều tháng liền .",
        "ông obama , đảng dân_chủ , gặp tỷ_phú trump , đảng cộng_hoà , tại phòng bầu_dục hôm 10/11 , hai ngày sau khi ông đắc_cử .",
        "theo trump , obama đã nói về những điều ông coi là rắc_rối lớn nhất ở mỹ .",
        "\" tôi có một cuộc gặp tuyệt_vời với tổng_thống obama \" , ông trump cho_biết .",
        "\" tôi thực_sự rất thích ông ấy .",
        "ông ấy nói những điều rất tốt_đẹp sau cuộc gặp và tôi cũng nói những điều rất tốt_đẹp về ông ấy \" .",
        "tổng_thống obama , từng công_kích ông trump khi vận_động cho ứng_viên tổng_thống đảng dân_chủ hillary_clinton , nêu rõ ông sẽ gạt bỏ bất_đồng để đảm_bảo quá_trình chuyển_giao quyền_lực diễn ra suôn_sẻ và bảo_vệ một trụ_cột dân_chủ mỹ .",
        "như_tâm"
    ],
    "image": [
        "tổng_thống đắc_cử donald_trump và tổng_thống barack_obama phát_biểu với báo_giới sau cuộc gặp tại nhà_trắng hôm 10/11 ."
    ],
    "label": [
        0,
        3,
        6
    ]
}