{
    "title": "trump nói vấn_đề triều_tiên cần được xử_lý nhanh_chóng",
    "abstract": "tổng_thống mỹ kêu_gọi xử_lý \" nhanh_chóng \" mối đe_doạ từ chương_trình hạt_nhân và tên_lửa_đạn_đạo của triều_tiên .",
    "article": [
        "tổng_thống mỹ donald_trump phát_biểu tại vườn_hồng , nhà_trắng , ngày 26/6 .",
        "\" chính_quyền triều_tiên đang tạo ra nhiều rắc_rối lớn và là vấn_đề cần phải giải_quyết nhanh_chóng \" , afp dẫn lời tổng_thống mỹ donald_trump phát_biểu trước báo_giới tại vườn_hồng , nhà_trắng , ngày 26/6 sau khi hội_đàm lần đầu với thủ_tướng ấn_độ narendra_modi .",
        "tổng_thống trump cảm_ơn ấn_độ vì đã cùng mỹ \" áp_dụng các lệnh trừng_phạt mới với triều_tiên \" .",
        "ông coi việc chặn chương_trình hạt_nhân của triều_tiên là một ưu_tiên hàng_đầu trong chính_sách đối_ngoại .",
        "triều_tiên đang phát_triển tên_lửa_đạn_đạo có khả_năng mang đầu đạn hạt_nhân tầm bắn tới mỹ dù bị cộng_đồng quốc_tế chỉ_trích và trừng_phạt .",
        "tổng_thống trump từng tuyên_bố sẽ \" không để điều này xảy ra \" và không loại_trừ lựa_chọn nào khi đối_phó triều_tiên .",
        "như_tâm"
    ],
    "image": [
        "tổng_thống mỹ donald_trump phát_biểu tại vườn_hồng , nhà_trắng , ngày 26/6 ."
    ],
    "label": [
        1,
        3
    ]
}