{
    "title": "‘ đua ’ cùng vietjet , vietnam_airlines chi hơn 730 tỷ trả cổ_tức",
    "abstract": "với 1,23 tỷ cổ_phiếu đang lưu_hành , cổ_đông của vietnam_airlines sẽ nhận được 735 tỷ đồng vào đầu tháng 10 tới .",
    "article": [
        "tổng_công_ty hàng_không việt_nam ( vietnam_airlines ) vừa có thông_báo thực_hiện chi_trả cổ_tức năm 2016 bằng tiền cho cổ_đông .",
        "cụ_thể , hãng này sẽ trả cổ_tức tỷ_lệ 6 % ( 1 cổ_phiếu mệnh_giá 10.000 đồng sẽ nhận được 600 đồng ) .",
        "hiện số_lượng cổ_phiếu đang lưu_hành của vietnam_airlines là 1,23 tỷ cổ_phiếu , ước_tính tổng_số tiền chi_trả cổ_tức lần này khoảng 735 tỷ đồng .",
        "ngày đăng_ký cuối_cùng là ngày 1/9/2017 và việc chi_trả cổ_tức bằng tiền_mặt sẽ được thực_hiện sau đó một tháng – tức từ ngày 2/10/2017 .",
        "mới_đây , hãng hàng_không giá rẻ được coi là đối_thủ của vietnam_airlines là vietjet_air cũng công_bố trả cổ_tức đợt 1 năm 2017 với tỷ_lệ 20 % ( 01 cổ_phiếu mệnh_giá 10.000 đồng nhận được 2.000 đồng ) .",
        "ngày đăng_ký cuối_cùng là 31/7 , và cổ_tức sẽ được vietjet_air thanh_toán cho cổ_đông vào ngày 15/8 .",
        "với vốn_điều_lệ gần 3.224 tỷ đồng , vietjet sẽ chi gần 645 tỷ đồng để trả cổ_tức đợt này cho cổ_đông .",
        "chốt phiên giao_dịch chiều ngày 20/7 , giá cổ_phiếu hvn của vietnam_airlines giảm xuống còn 26.000 đồng / cp .",
        "trong khi đó vietjet_air vẫn không làm cổ_đông thất_vọng khi giá cổ_phiếu tăng liên_tục vài ngày qua lên con_số 127.000 đồng - gấp 5 lần cổ_phiếu hãng hàng_không quốc_gia việt_nam .",
        "hoa_liên"
    ],
    "image": [],
    "label": [
        2,
        1,
        5
    ]
}