{
    "title": "con đường công_danh của cựu tổng_giám_đốc bidv vừa đột_ngột qua_đời",
    "abstract": "sau khi ông trần_bắc_hà nghỉ hưu , ông trần_anh_tuấn là người được lựa_chọn giữ vị_trí cao nhất lãnh_đạo ngân_hàng bidv trong giai_đoạn đầy biến_động .",
    "article": [
        "nguyên tổng_giám_đốc ngân_hàng đầu_tư và phát_triển việt_nam ( bidv ) trần_anh_tuấn đã qua_đời hôm 16/8 sau một cơn đột_quỵ .",
        "ông trần_anh_tuấn ( sn 1958 ) , nguyên_quán quảng_ngãi , sinh ra tại yên_bái , địa_chỉ thường_trú tại phường tứ_liên , quận tây_hồ , hà_nội .",
        "nắm trong tay tấm bằng thạc_sĩ kinh_doanh , ông tuấn tham_gia bidv từ năm 1981 .",
        "trong quãng thời_gian từ năm 1989 đến 1998 , ông đã nắm giữ các chức_vụ : giám_đốc chi_nhánh bidv tại gia_lai - kon_tum , phó tổng_giám_đốc bidv .",
        "từ năm 1998 - 2007 ông là phó tổng_giám_đốc , thành_viên hđqt bidv .",
        "từ năm 2008 đến 2012 , ông đảm_nhận vị_trí tổng_giám_đốc bidv .",
        "từ tháng 5/2012 ông được bầu làm uỷ_viên hđqt bidv .",
        "đặc_biệt , trong thời_gian này , ông trần_anh_tuấn được giao nhiệm_vụ phụ_trách hđqt sau khi ông trần_bắc_hà nghỉ hưu kể từ ngày 01/09/2016 .",
        "dù không chính_thức là chủ_tịch hđqt , nhưng đây cũng là khoảng thời_gian ông ngồi ghế cao nhất trong ngân_hàng khi là người thực_hiện chức_trách , nhiệm_vụ và quyền_hạn của chủ_tịch hđqt bidv .",
        "năm 2017 là năm ông tuấn điều_hành bidv một_cách trọn_vẹn trên cương_vị phụ_trách hđqt với nhiều tín_hiệu tăng_trưởng tích_cực thời \" hậu trần_bắc_hà \" .",
        "trong đó , tổng tài_sản của bidv đạt 1.176.000 tỷ đồng , tăng_trưởng 16,7 % so với năm 2016 , tăng 8,42 % so với cùng kỳ năm trước .",
        "tổng nguồn vốn huy_động đạt 1.106.517 tỷ đồng , tăng 17,9 % so với năm 2016 .",
        "tổng quy_mô tín_dụng và đầu_tư đạt gần 1.1136.778 tỷ đồng , tăng_trưởng 18 % so với năm trước .",
        "trong đó cho vay nền kinh_tế đạt 862.604 tỷ đồng , tăng_trưởng 17 % , chiếm 13,12 % quy_mô tín_dụng toàn ngành ngân_hàng .",
        "riêng chỉ_tiêu lợi_nhuận trước thuế của bidv trong năm này là 8.800 tỷ đồng .",
        "đến ngày 2/5/2018 , ông trần_anh_tuấn từ_nhiệm để nghỉ hưu , nhường \" ghế nóng \" bidv cho ông bùi_quang_tiên và đến tháng 11/2018 , ông phan_đức_tú được chính_thức bầu làm người kế_nhiệm chức chủ_tịch hđqt ngân_hàng bidv thay ông trần_bắc_hà sau hơn 2 năm bỏ trống .",
        "bá_di"
    ],
    "image": [
        "ông trần_anh_tuấn qua_đời ngày 16/8/2019 ở tuổi 61 ."
    ],
    "label": [
        15,
        8
    ]
}