{
    "title": "dự_báo thời_tiết 5/12 : trước không_khí lạnh tràn về , nhiệt_độ miền bắc cao nhất 30 độ",
    "abstract": "trước khi không_khí lạnh ảnh_hưởng tới miền bắc gây rét đậm thì ngày 5/12 miền bắc trời oi nóng , nhiệt_độ cao nhất 30 độ .",
    "article": [
        "dự_báo thời_tiết tây_bắc_bộ : nhiều mây , có mưa vài nơi , sáng sớm có sương_mù và sương_mù nhẹ rải_rác , trưa chiều giảm mây trời nắng .",
        "gió nhẹ .",
        "độ_ẩm từ 56 - 98 % .",
        "nhiệt_độ thấp nhất từ 21 - 24 độ , riêng khu tây_bắc 17-20 độ .",
        "nhiệt_độ cao nhất từ 27 - 30 độ , có nơi trên 30 độ .",
        "thời_tiết đông_nam_bộ : nhiều mây , có mưa vài nơi , sáng sớm có sương_mù và sương_mù nhẹ rải_rác , trưa chiều giảm mây trời nắng .",
        "gió đông nam cấp 2-3 .",
        "độ_ẩm từ 60 - 98 % .",
        "nhiệt_độ thấp nhất từ 20 - 23 độ , vùng núi có nơi dưới 20 độ .",
        "nhiệt_độ cao nhất từ 27 – 30 độ .",
        "dự_báo thời_tiết nam_bộ : mây thay_đổi , chiều_tối và đêm có mưa_rào và dông vài nơi , ngày nắng .",
        "gió đông bắc đến đông cấp 2 - 3 .",
        "độ_ẩm từ 50 - 95 % .",
        "nhiệt_độ thấp nhất từ 23 – 26 độ .",
        "nhiệt_độ cao nhất từ 31 – 34 độ .",
        "dự_báo : khoảng chiều_tối và đêm 6/12 , bộ_phận không_khí lạnh này sẽ ảnh_hưởng đến khu đông_bắc bắc_bộ , ngày 7/12 ảnh_hưởng đến các nơi khác ở bắc_bộ và bắc_trung_bộ , sau đó ảnh_hưởng đến một_số nơi ở trung_trung_bộ ; gió chuyển_hướng đông bắc trong đất_liền cấp 3 , vùng_ven biển cấp 3-4 .",
        "từ đêm 6/12 , khu_vực đông_bắc_bắc_bộ trời chuyển rét , từ ngày 7/12 các nơi khác ở bắc_bộ và bắc_trung_bộ trời chuyển rét ; nhiệt_độ thấp nhất phổ_biến 14-17 độ , ở vùng núi bắc_bộ 11-13 độ .",
        "ở vịnh bắc_bộ từ đêm 6/12 , gió chuyển_hướng đông_bắc mạnh dần lên cấp 6-7 , giật cấp 8 ; biển động mạnh .",
        "từ ngày 7/12 , trên khu_vực bắc_biển_đông gió đông bắc mạnh dần lên cấp 7 , giật cấp 8 ; biển động mạnh .",
        "cảnh_báo mưa lớn , dông , lốc , sét : do ảnh_hưởng của không_khí lạnh nén rãnh áp_thấp nên từ chiều_tối ngày 6/12 , các tỉnh ở vùng núi phía bắc có mưa_rào và dông rải_rác , sau đó vùng mưa mở_rộng xuống các khu_vực khác ở bắc_bộ .",
        "từ ngày 7/12 , các tỉnh thanh_hoá đến thừa_thiên_huế có mưa , mưa vừa , có nơi mưa to và dông .",
        "trong cơn dông có khả_năng xảy ra lốc , sét , mưa_đá và gió giật mạnh .",
        "cấp_độ rủi_ro thiên_tai do mưa lớn , lốc , sét : cấp 1",
        "thời_tiết hà_nội : gần sáng ngày 7/12 có mưa_rào và dông , trời chuyển rét , nhiệt_độ thấp nhất phổ_biến 15-18 độ .",
        "dưới đây là dự_báo thời_tiết các vùng và một_số tỉnh_thành trên cả nước :",
        "phong_linh",
        "thiết_kế : nguyễn_yến"
    ],
    "image": [],
    "label": [
        16,
        15,
        4
    ]
}