{
    "title": "khởi tố vụ án phá rừng sát biên giới trong tết nguyên đán",
    "abstract": "công_an nhận định ngoài bị_can bị khởi_tố vụ phá rừng nghiêm trọng này còn đồng phạm nên vẫn đang tiếp tục mở rộng điều tra ...",
    "article": [
        "liên_quan đến vụ phá rừng nghiêm trọng xảy ra tại xã quảng trực , tuy đức ( đắk nông ) , công_an đã khởi tố vụ án , khởi tố bị can để đấu tranh làm rõ …",
        "sáng 17-12 , công_an huyện tuy_đức , cho biết đã khởi_tố vụ án , khởi_tố bị_can đối_với vũ_văn_quyền ( 35 tuổi , ngụ xã quảng_trực ) để điều_tra , làm rõ hành_vi vi_phạm các quy_định về khai_thác , bảo_vệ rừng và quản_lý lâm_sản theo điều 232 , bộ luật_hình_sự 2015 .",
        "công_an huyện tuy_đức ( đắk_nông ) đã chuyển hồ_sơ sang vksnd cùng cấp , đề_nghị phê_chuẩn lệnh khởi_tố 1 đối_tượng liên_quan đến vụ phá rừng tại xã quảng_trực .",
        "tuy_nhiên , lực_lượng chức_năng nhận_định vụ phá rừng này có quy_mô lớn , nhiều khả_năng vẫn có đối_tượng đồng_phạm nên tiếp_tục thu_thập chứng_cứ , đấu_tranh để làm rõ .",
        "trước đó , như tuổi trẻ online đã đưa tin , ubnd huyện tuy đức đã giao công_an phối hợp với hạt kiểm lâm huyện để điều tra hai vụ phá rừng , vận chuyển lâm sản trái phép quy_mô lớn nêu trên .",
        "vụ phá rừng xảy ra tại tiểu khu 1488 , thuộc sự quản_lý của ubnd xã quảng_trực , huyện tuy_đức , đắk_nông được xác định xảy ra trong dịp tết nhưng mới được phát hiện .",
        "theo ghi nhận bước đầu , có 69 cây_gỗ ( chủ yếu là bằng lăng ) bị đốn hạ nằm rải_rác tại các khoảnh 2 , 3 , 4 và 5 , thuộc tiểu_khu 1488 .",
        "phần_lớn số cây bằng_lăng này có đường kính 20-40 cm , sau khi đốn hạ đã bị cắt xẻ , vận_chuyển khỏi hiện_trường , chỉ còn lại phần gốc .",
        "theo báo cáo ngành chức năng , tại hiện_trường phá rừng thu_giữ được 23m3 gỗ tròn chủng_loại bằng_lăng .",
        "ngoài ra , mở rộng kiểm tra ra khu vực khác , kiểm lâm huyện tuy đức còn thu giữ thêm 8m3 gỗ nữa nằm rải rác trên các tuyến đường mòn .",
        "trong khi đó , thống_kê sơ_bộ của hạt kiểm_lâm tuy_đức , có 69 cây_gỗ ( chủ_yếu là bằng_lăng ) bị cưa hạ để khai_thác gỗ trái_phép , ước_tính có gần 100m3 gỗ tròn đã bị khai_thác ."
    ],
    "image": [
        "gỗ bị đốn hạ nằm rài rác trong rừng - ảnh : l.đ .",
        "nhiều cây gỗ bị đốn hạ có đường kính khá lớn - ảnh : l.đ ."
    ],
    "label": [
        0,
        9,
        1
    ]
}