{
    "title": "bắt nghi can trộm_cắp rồi ngủ quên tại ... lan_can nhà dân",
    "abstract": "sau khi đột_nhập nhà dân trộm_cắp tài_sản tẩu_thoát , kẻ_trộm quá buồn_ngủ nên ngủ quên tại ... lan_can nhà dân .",
    "article": [
        "ngày 30-10 , công_an quận 7 , tp. hcm cho_biết đang tạm giữ hình_sự nguyễn_ngô_khương ( 26 tuổi , ngụ khu_phố 2 , phường phú_mỹ , quận 7 ) để điều_tra về hành_vi trộm_cắp tài_sản .",
        "theo thông_tin ban_đầu , lúc 1h30 sáng 29-9 , do cần tiền tiêu_xài nên khương lảng_vảng đi \" nhập nha \" trộm tài_sản .",
        "khi đi đến một căn nhà trên đường huỳnh_tấn_phát ( khu_phố 3 , phường phú_mỹ ) , khương đã dùng gạch đập bể cửa_kính , đột_nhập vào nhà .",
        "vào trong nhà , khương lục_lọi tìm tài_sản và trộm được một túi_xách ( bên trong có một điện_thoại_di_động và 6 triệu đồng ) của chị p. t.t . t .",
        "( 28 tuổi , ngụ tại căn nhà bị đột_nhập ) rồi tìm cách tẩu_thoát ra ngoài .",
        "sau đó , khương leo lên lan_can lầu 1 của một nhà dân cách đó không xa ( khu_phố 3 , phường phú_mỹ ) ẩn_nấp .",
        "tại đây , khương mở túi_xách , lấy tài_sản vừa trộm được bỏ vào túi quần .",
        "lúc này do quá buồn_ngủ nên khương ngủ quên luôn tại ... lan_can lầu 1 nhà dân .",
        "đến khoảng 6h15 sáng 29-10 , chị n.t . b.l .",
        "( 33 tuổi , là thành_viên trong căn nhà ) phát_hiện khương đang ngủ tại lan_can lầu 1 .",
        "nghi_vấn tội_phạm nên chị l. âm_thầm báo cho công_an phường phú_mỹ xuống xử_lý .",
        "nhận tin báo , lực_lượng công_an phường xuống hiện_trường thì khương vẫn còn … say_sưa ngủ .",
        "lực_lượng công_an đã mời khương về trụ_sở công_an phường làm_việc .",
        "tại cơ_quan công_an , bước_đầu khương khai nhận toàn_bộ hành_vi trộm_cắp tài_sản của mình .",
        "hiện công_an đang tạm giữ hình_sự khương , tiếp_tục điều_tra làm rõ ."
    ],
    "image": [],
    "label": [
        7,
        0
    ]
}