{
    "title": "tỏ_tình bằng xe lamborghini và cái kết đắng",
    "abstract": "trên mạng xã_hội , nhiều người chia_sẻ đoạn clip về một thanh_niên trung_quốc tỏ_tình với cô_gái nga bằng xe lamborghini .",
    "article": [
        "anh ta liên_tục nói : \" anh rất giàu .",
        "anh có_thể mua cho em tất_cả .",
        "hãy cưới anh \" .",
        "theo south_china_morning_post , sự_việc trên diễn ra ở tỉnh hồ_nam ( trung_quốc ) một năm trước .",
        "trái với sự tưởng_tượng của nhiều người , cô_gái kêu lên : \" đừng làm tôi áp_lực \" .",
        "cô nói thêm : \" tôi không muốn .",
        "chúng_ta sinh ra không phù_hợp cho nhau .",
        "xin đừng làm điều này nữa \" .",
        "đám đông liên_tục hỏi đầy ngạc_nhiên : \" anh ấy đã mua chiếc xe mà cô thích \" .",
        "nhưng cô_gái đáp : \" chỉ vì anh giàu thôi sao ?",
        "khi bị từ_chối thẳng_thừng , thanh_niên giàu_có đập phá đồ_vật xung_quanh , khiến nhiều người sợ_hãi .",
        "tờ daily_mail ( anh ) đưa tin video này quay ngày 21-10-2018 bên ngoài một trung_tâm thương_mại ở hồ_nam ( trung_quốc ) .",
        "những ngày gần đây , cư_dân mạng châu_á khiến video này hot trở_lại .",
        "nhiều cư_dân mạng việt_nam còn liên_tưởng đến câu nói đang được bàn_luận sôi_nổi mấy ngày_nay trên mạng xã_hội việt_nam \" tiền nhiều để làm gì ?"
    ],
    "image": [
        "cảnh tỏ_tình ( trái ) và phản_ứng của chàng thanh_niên khi bị từ_chối ( phải ) - ảnh chụp màn_hình"
    ],
    "label": [
        4,
        3,
        13
    ]
}