{
    "title": "o bánh_mì đến rồi !",
    "abstract": "thương lũ trẻ nghèo người_dân tộc pa cô ở vùng biên giới a_ngo , huyện đắkrông ( quảng trị ) , bốn cô_gái nảy ra ý tưởng mỗi sáng chở một thùng bánh mì lưu động lên các bản làng .",
    "article": [
        "hôm_nay có sữa ...",
        "6g sáng thứ tư giữa tháng 9 .",
        "bản la_lay ( xã_a_ngo ) còn lờ mờ sương phủ .",
        "trước sân nhà trưởng bản hồ văn_reo có một khoảng trống khá rộng .",
        "một đám trẻ con chừng 50 em đã ngồi túm tụm ở đó từ sớm .",
        "năm chục cặp mắt cứ hướng ra con đường trước mặt chờ đợi .",
        "15 phút , một chiếc xe máy đến .",
        "nghe tiếng xe , lũ trẻ nhổm khỏi chỗ ngồi chạy ra mép đường .",
        "hồ văn_phơi , một đứa trong nhóm , reo lên : \" o bánh mì đến rồi !",
        "o bánh mì đến rồi ! \"",
        "cả đám trẻ nhao lên chạy ùa ra đón chiếc xe máy .",
        "vừa dựng được chiếc xe xuống , chúng vây quanh hai cô gái cùng chiếc thùng to ở phía sau xe .",
        "tường vy , một trong hai cô gái , mở chiếc thùng ra , mùi bánh mì mới ra lò thơm phức .",
        "trong khi phương_nhi , cô gái còn lại , mở chiếc túi nhỏ treo phía trước , nói : \" hôm_nay mới có người gửi cho mấy hộp sữa đặc nên các cháu sẽ được ăn mì sữa chứ không phải bánh_mì ' chay ' như mọi hôm nữa \" .",
        "phương_nhi vừa nói xong , đám trẻ reo ầm lên sung sướng .",
        "tường vy cho_biết la_lay là bản cách xa trung_tâm xã đến gần 10km nên hai chị em phải dậy sớm hơn mọi ngày để đi lấy bánh mì .",
        "chở vào tới bản la_lay và phát bánh mì phải xong trước 7h sáng để hai bạn kịp quay ngược ra đi làm cho kịp giờ .",
        "ngoài tường vy và phương_nhi , chị hồng và thêm một bạn nữ khác tên ngọc ánh cũng thay phiên nhau chở bánh mì vào bản la_lay phát cho đám trẻ .",
        "theo chị hồng - nhóm trưởng \" o bánh_mì \" - những ngày đầu mới chở bánh mì vào bản , mấy chị em phải đưa đến từng nhà cho các em .",
        "qua gần một năm các em đã quen và nắm rõ ngày xe bánh mì về bản mình để tập trung đến nhận .",
        "mỗi người góp một phần tấm lòng vào ổ bánh_mỳ",
        "chị hồng quê hải lăng , mới lên hợp đồng làm nhân_viên văn phòng của ubnd xã a_ngo được hai năm rưỡi .",
        "ngọc ánh là nhân_viên trạm y tế xã a_ngo .",
        "còn tường vy và phương_nhi là nhân_viên tại xã a_bung kế bên .",
        "khi mới lên vùng biên giới này , điều mấy chị em ám ảnh nhất chính là hình ảnh những đứa trẻ ở các bản làng .",
        "nhiều đứa đến áo quần cũng không có mặc .",
        "nhiều bữa về bản công tác , mấy chị em xót lòng khi thấy bữa cơm của những gia đình đồng bào pa cô ở đây chỉ có rau rừng hoặc măng rừng với muối ớt .",
        "chính vì thế , khi chị hồng đưa ý tưởng về thùng bánh mì lưu động , mấy chị em ủng hộ ngay .",
        "mấy tháng đầu , bốn chị em mỗi người góp 300.000 đồng mỗi tháng để mua bánh mì .",
        "thời điểm đó mấy chị em chỉ có thể mang thùng bánh mì đến cho đám trẻ ở bản_a đang .",
        "sau đó ông nguyễn bá duyệt , đồn trưởng đồn biên phòng cửa khẩu la_lay , biết chuyện đã xin góp mỗi tháng 500.000 đồng .",
        "nhờ đó nhóm của hồng mở thêm một thùng bánh mì nữa chở lên bản la_lay là bản xa nhất của xã a_ngo .",
        "sau đó , một số bạn bè của nhóm đã gom góp thêm được vài triệu đồng nên thùng bánh mì được mở_rộng đến bản a_đeng và a_rong .",
        "mỗi tuần , thùng bánh_mì sẽ đến mỗi bản một lần .",
        "biết nhóm của hồng lấy mỗi sáng cả trăm ổ bánh mì để phát cho đám trẻ , một chủ lò bánh mì ở xã a_ngo đã giảm 100.000 đồng tiền bánh_mì mỗi tháng ."
    ],
    "image": [
        "thùng bánh_mì lưu động của các o bánh_mì - ảnh : t.vy .",
        "phương_nhi bỏ thêm sữa vào ổ mỳ phát cho đám trẻ vùng cao - ảnh : t.vy"
    ],
    "label": [
        24,
        27,
        12
    ]
}