{
    "title": "xăng giảm hai kỳ liên_tiếp giúp cpi giảm gần 0,3 %",
    "abstract": "tổng_cục thống_kê vừa công_bố chỉ_số giá tiêu_dùng ( cpi ) tháng 11-2018 với mức giảm 0,29 % so với tháng trước do tác_động của việc giảm_giá xăng_dầu , nhu_cầu tiêu_dùng điện giảm .",
    "article": [
        "như_vậy , so với cùng kỳ năm trước , cpi tăng 3,46 % và tăng 3,24 % so với tháng 12 năm trước , cpi bình quân 11 tháng đầu năm 2018 so với cùng kỳ năm trước tăng 3,59 % .",
        "trong 11 nhóm hàng_hoá và dịch_vụ để tính chỉ_số cpi , có 7 nhóm hàng tăng giá và 4 nhóm hàng giảm_giá .",
        "trong đó , đáng chú_ý là giá xăng_dầu trong nước được điều_chỉnh giảm trong hai kỳ của tháng 11 , nên bình_quân tháng 11-2018 giá xăng_dầu giảm 4,1 % , đóng_góp giảm cpi chung 0,17 % .",
        "giá thịt heo cũng giảm 1,3 % so với tháng trước do nguồn cung heo hơi trên thị_trường dồi_dào , với tổng đàn tăng khoảng 2,8 % .",
        "từ ngày 1-11 , giá gas trong nước cũng được điều_chỉnh giảm 40.000 đồng / bình 12kg , giảm 9,18 % so với tháng 10-2018 , do giá gas thế_giới giảm .",
        "ngoài_ra là giá rau tươi giảm 0,68 % do thời_tiết thuận_lợi nên sản_lượng rau tươi dồi_dào và nhiều chủng_loại .",
        "trong tháng 11 , thời_tiết chuyển lạnh ở các tỉnh phía bắc nên nhu_cầu tiêu_dùng điện giảm làm cho giá điện sinh_hoạt giảm 0,64 % .",
        "một_số yếu_tố làm cpi tăng như giá lương_thực tăng 0,27 % , giá vật_liệu bảo_dưỡng nhà ở tăng 0,11 % , giá quần_áo may_sẵn , giày_dép , mũ nón tăng 0,26 % ...",
        "lạm_phát cơ_bản ( cpi sau khi loại_trừ lương_thực , thực_phẩm tươi_sống , năng_lượng và mặt_hàng do nhà_nước quản_lý bao gồm dịch vụ y tế và dịch vụ giáo dục ) tháng 11-2018 tăng 0,11 % so với tháng trước , tăng 1,72 % so với cùng kỳ năm trước , 11 tháng đầu năm 2018 so với cùng kỳ năm trước tăng 1,46 % .",
        "như_vậy , bình_quân 11 tháng đầu năm 2018 so với cùng kỳ , lạm_phát chung có mức tăng cao hơn lạm_phát cơ_bản .",
        "cơ_quan thống_kê cho_rằng thực_tế này phản_ánh biến_động giá chủ_yếu do việc tăng_giá lương_thực , thực_phẩm , giá xăng_dầu , giá dịch_vụ y_tế và giáo_dục .",
        "mức tăng lạm_phát cơ_bản từ tháng 1 đến tháng 11 năm nay so với cùng kỳ có biên_độ dao_động trong khoảng khá hẹp từ 1,18 % đến 1,72 % , bình_quân 11 tháng lạm_phát cơ_bản là 1,46 % thấp hơn mức kế_hoạch 1,6 % , cho thấy chính_sách tiền_tệ đã và đang được điều_hành ổn_định ."
    ],
    "image": [
        "xăng_dầu điều_chỉnh giảm 2 kỳ liên_tiếp trong tháng 11 làm cpi giảm - ảnh : chí_tuệ"
    ],
    "label": [
        8,
        2,
        6
    ]
}