{
    "title": "gởi thú cưng ngày tết , chủ ' bay ' 500.000 đồng / ngày",
    "abstract": "dịch_vụ trông giữ thú cưng xuyên tết đang hoạt_động hiệu_quả tại nhiều tỉnh_thành như tp. hcm , hà_nội , đà_nẵng ... giá trông 10 ngày tết gần bằng 1 tháng lương của công_chức .",
    "article": [
        "tại nhiều \" khách_sạn \" trông giữ chó mèo ở tp. hcm hiện đã kín gần hết phòng .",
        "giá trông giữ ngày tết cao gấp rưỡi hoặc gấp đôi ngày thường .",
        "phòng thường giá từ 150.000 đồng / ngày , phòng vip từ 300.000 đồng / ngày .",
        "một điểm trông giữ thú cưng ( q. 5 , tp. hcm ) báo_giá phòng vip cho thú cưng tối_đa 10kg là 300.000 đồng / ngày , có phòng vip cho \" khách \" tối_đa 40kg giá tới 500.000 đồng / ngày .",
        "tại các \" khách_sạn \" thú cưng , các bé chó mèo được bác_sĩ thú_y , nhân_viên theo_dõi sức_khoẻ thường_xuyên , chăm_sóc trong phòng có điều_hoà , giám_sát bởi hệ_thống camera 24/7 để chủ nuôi có_thể theo_dõi qua điện_thoại .",
        "ngoài việc tự đưa thú cưng đến gửi , nhiều nơi còn hỗ_trợ dịch_vụ đưa_đón hai chiều .",
        "bên cạnh đó , còn có dịch_vụ spa cho chó mèo , \" tút lại nhan_sắc \" có giá 100.000-650.000 đồng / lần .",
        "để chuẩn_bị tết , anh hồ_trung_trực ( làm_việc tại một cửa_hàng thú cưng ) chia_sẻ theo thống_kê sơ_bộ năm nay lượng khách tăng 50 % , khách cũ quay lại khoảng 80 % .",
        "\" công_ty nhập về chuồng mới , hiện_đại hơn , có hệ_thống lọc khí , hệ_thống xịt nước tự_động \" , anh trực nói .",
        "không_chỉ nhận trông giữ chó mèo , một_số nơi còn trông giữ chuột hamster , nhím kiểng , sóc đất , bọ ú , thỏ giá từ 8.000-45.000 đồng / ngày , đã bao_gồm thức_ăn và lót chuồng nhưng khách phải đem theo lồng ."
    ],
    "image": [
        "phòng vip cho chó được trang_trí hoa_lá , cửa_kính , đèn led tại một cơ_sở giữ thú ở tp. hcm - ảnh : bông_mai"
    ],
    "label": [
        3,
        0
    ]
}