{
    "title": "ôtô đấu đầu , 4 người thiệt_mạng",
    "abstract": "sau cú đâm trực_diện , cả 4 người đi trên xe 4 chỗ tử_vong tại_chỗ , 3 người trên ôtô 7 chỗ bị_thương nặng .",
    "article": [
        "theo lãnh_đạo sở giao_thông vận_tải hà_giang , khoảng 20h ngày 29/2 , trên quốc_lộ 2 , đoạn qua huyện vị_xuyên , cách tp hà_giang khoảng 15 km , xe 7 chỗ và 4 chỗ mang biển số hà_giang lưu_thông ngược chiều đã đấu đầu nhau .",
        "4 người trên xe 4 chỗ tử_vong tại_chỗ , 3 người trên xe 7 chỗ bị_thương nặng .",
        "chiếc xe bị nát sau cú va_chạm mạnh .",
        "sau tai_nạn , người_dân quanh khu_vực đã nhanh_chóng đưa các nạn_nhân bị_thương đi cấp_cứu , lực_lượng chức_năng tiến_hành khám_nghiệm hiện_trường .",
        "theo đại_diện sở giao_thông vận_tải hà_giang , khu_vực xảy ra tai_nạn địa_hình không phức_tạp , nên nhiều khả_năng phương_tiện chạy nhanh và không làm_chủ được tốc_độ .",
        "đoàn_loan"
    ],
    "image": [
        "chiếc xe bị nát sau cú va_chạm mạnh ."
    ],
    "label": [
        1,
        2,
        3
    ]
}