{
    "title": "phó chủ_tịch xã bị kỷ_luật vì tổ_chức đám_cưới nhận con dâu 14 tuổi",
    "abstract": "con_trai 21 tuổi của ông phó chủ_tịch xã được gia_đình tổ_chức đám_cưới với cô_dâu nhí mới 14 tuổi .",
    "article": [
        "tối 9/10 , trao_đổi với vnexpress , ông võ_đình_quang , chủ_nhiệm uỷ_ban kiểm_tra huyện_uỷ vũ_quang ( hà_tĩnh ) xác_nhận ông nguyễn_minh_tường ( phó chủ_tịch xã hương_minh ) trong những ngày tới sẽ bị yêu_cầu viết kiểm_điểm về việc hôm_qua đã tổ_chức cưới bé gái 14 tuổi cho con_trai út 21 tuổi .",
        "theo ông quang , trước khi tổ_chức đám_cưới , con_trai ông tường không đăng_ký kết_hôn qua chính_quyền xã , vì_thế sự_việc không được ngăn_chặn kịp_thời .",
        "“ sai_phạm của ông tường khi tổ_chức tảo_hôn cho con đã quá rõ .",
        "chúng_tôi đang để ông tường lo_toan việc cho gia_đình sau đám_cưới .",
        "đầu tuần tới sẽ yêu_cầu viết bản kiểm_điểm tự nhận hình_thức kỷ_luật ” , ông quang nói .",
        "một phó chủ_tịch huyện vũ_quang chia_sẻ , đây là việc hy_hữu tại địa_phương .",
        "sau khi có quyết_định kỷ_luật về đảng , ông tường sẽ xử_lý về mặt chính_quyền .",
        "cô_dâu nhí 14 tuổi được gia_đình cho nghỉ học từ tháng 9 với lý_do trình_bày với nhà_trường là \" ở nhà chữa bệnh \" .",
        "đức_hùng"
    ],
    "image": [],
    "label": [
        0,
        7,
        1
    ]
}