{
    "title": "hai xe_buýt đấu đầu trên quốc_lộ",
    "abstract": "hai xe_buýt cùng công_ty đâm nhau khi chạy trên quốc_lộ 46 ( nghệ_an ) khiến một tài_xế gãy chân , kẹt trong cabin .",
    "article": [
        "sáng 8/10 , xe_buýt đông_bắc biển nghệ_an chở 7 người , chạy hướng thành_phố vinh - huyện thanh_chương trên quốc_lộ 46 .",
        "xe tới địa_phận xã đồng_văn ( huyện thanh_chương ) đã đâm trúng xe_buýt khác cùng công_ty chạy hướng ngược_lại .",
        "hai xe_buýt đấu đầu trên quốc_lộ .",
        "tại nạn khiến một tài_xế bị gãy chân , mắc_kẹt trong cabin , được lực_lượng cứu_hộ đưa ra ngoài sau đó .",
        "tài_xế còn lại và một hành_khách bị_thương nhẹ .",
        "nhiều mảnh vỡ từ hai chiếc xe gặp nạn vương_vãi tại hiện_trường .",
        "công_an huyện thanh_chương đến phân_luồng giao_thông và khám_nghiệm hiện_trường để điều_tra nguyên_nhân tai_nạn ."
    ],
    "image": [
        "hai xe_buýt đấu đầu trên quốc_lộ ."
    ],
    "label": [
        3,
        1,
        0
    ]
}