{
    "title": "tài_xế bất_tỉnh , kẹt cứng trong ôtô sau tai_nạn",
    "abstract": "chiếc xe được cho là chạy tốc_độ cao đâm mạnh vào lan cầu_vượt , quay đầu vỡ nát , nam tài_xế 26 tuổi mắc_kẹt ở ghế lái được người_dân dùng xà_beng giải_cứu .",
    "article": [
        "hiện_trường vụ tai_nạn .",
        "15h30 ngày 22/6 , anh nguyễn_văn_đồng ( 26 tuổi ) trú tại huyện tân_kỳ ( nghệ_an ) điều_khiển ôtô hyundai i10 chạy trên quốc_lộ 1a hướng nam - bắc .",
        "tới giữa cầu_vượt đường_sắt tại xã nghi_kim ( tp vinh ) , xe mất lái lao sang bên phải đâm mạnh vào lan_can sắt .",
        "cú đâm khiến chiếc xe dập nát , quay đầu 180 độ với hướng lưu_thông , bung túi khí , tài_xế chấn_thương nặng và bất_tỉnh , kẹt cứng trong ghế lái .",
        "một_số người tham_gia giao_thông và người_dân phải dùng xà_beng và các vật_dụng cạy cửa giải_cứu đưa tài_xế nhập_viện .",
        "tai hiện_trường , nhiều mảnh vỡ ôtô văng tung_toé , một đoạn lan bằng sắt của cầu bị gãy gập .",
        "nhiều người phán_đoán thời_điểm xảy ra tai_nạn chiếc xe chạy với tốc_độ cao .",
        "cảnh_sát giao_thông thành_phố vinh đang điều_tra tai_nạn .",
        "phương_linh"
    ],
    "image": [
        "hiện_trường vụ tai_nạn .",
        "bộ_phận ghế lái chiếc xe bị nạn vỡ nát ."
    ],
    "label": [
        3,
        1,
        4
    ]
}