{
    "title": "taxi chở 3 hành_khách đi sân_bay cam_ranh lao xuống vực",
    "abstract": "tài_xế cùng 3 hành_khách may_mắn thoát nạn khi chiếc taxi lao xuống vực sâu 3 m ở đèo cù_hin , khánh_hoà .",
    "article": [
        "hiện_trường vụ taxi rơi xuống vực .",
        "ngày 17/8 , tài_xế taxi bốn chỗ chở 3 hành_khách từ tp nha_trang đi sân_bay quốc_tế cam_ranh , khánh_hoà .",
        "khi chạy trên đại_lộ nguyễn_tất_thành , ôtô bất_ngờ lao xuống vực sâu chừng 3 m ở đèo cù_hin .",
        "tai_nạn khiến taxi vỡ kính , hư_hỏng .",
        "tài_xế cùng 3 hành_khách may_mắn thoát nạn , tự mở_cửa thoát ra ngoài trong tình_trạng hoảng_loạn .",
        "họ lúc sau được một xe khác đến đón để tiếp_tục hành_trình .",
        "theo đội cảnh_sát giao_thông nha_trang , tài_xế taxi đã lấn làn để vượt ôtô khách phía trước nhưng gặp đoạn cua gắt đã không kịp xử_lý , dẫn đến tai_nạn .",
        "an_phước"
    ],
    "image": [
        "hiện_trường vụ taxi rơi xuống vực ."
    ],
    "label": [
        2,
        4
    ]
}