{
    "title": "ông nguyễn_đức_chung tái đắc_cử chủ_tịch tp hà_nội",
    "abstract": "bộ_máy chính_quyền hà_nội nhiệm_kỳ 2016-2021 đã được hđnd thành_phố thông_qua , trong đó các chức_danh chủ_chốt như chủ_tịch , phó chủ_tịch hđnd , ubnd đều giữ nguyên .",
    "article": [
        "sáng 14/6 , hđnd tp hà_nội khoá 15 họp kỳ thứ nhất bầu các chức_danh chủ_tịch hđnd , chủ_tịch ubnd thành_phố nhiệm_kỳ 2016-2021 .",
        "với 100 % đại_biểu có_mặt đồng_ý , bà nguyễn_thị_bích_ngọc , chủ_tịch hđnd nhiệm_kỳ 2011-2016 tái_cử nhiệm_kỳ 2016-2021 .",
        "bà ngọc sinh năm 1961 , quê xã đông_quang ( ba vì , hà_nội ) , là cử_nhân luật .",
        "hai phó chủ_tịch hđnd thành_phố tái_cử là ông nguyễn_ngọc_tuấn và bà phùng_thị_hồng_hà với tỷ_lệ phiếu trên 96 % .",
        "với hơn 96 % phiếu đồng_ý , ông nguyễn_đức_chung tiếp_tục giữ chức chủ_tịch ubnd tp hà_nội khoá mới .",
        "ông nguyễn_đức_chung .",
        "ông chung sinh năm 1967 , quê kinh_môn ( hải_dương ) , là điều_tra_viên cao_cấp , tiến_sĩ luật , cử_nhân kinh_tế .",
        "ông được phong danh_hiệu anh_hùng lực_lượng_vũ_trang khi mới 37 tuổi và từng kinh_qua các chức_vụ : phó giám_đốc công_an thành_phố , thủ_trưởng cơ_quan cảnh_sát điều_tra , giám_đốc công_an hà_nội .",
        "với hơn 90 % đại_biểu bỏ_phiếu đồng_tình , 6 phó chủ_tịch ubnd thành_phố đương_nhiệm tiếp_tục giữ chức trong nhiệm_kỳ mới , gồm các ông : nguyễn_thế_hùng , lê_hồng_sơn , nguyễn_văn_sửu , nguyễn_doãn_toản , nguyễn_quốc_hùng , ngô_văn_quý .",
        "lan_hạ"
    ],
    "image": [
        "ông nguyễn_đức_chung ."
    ],
    "label": [
        0,
        8,
        7
    ]
}