{
    "title": "ôtô bmw húc văng nhiều xe_máy ở sài_gòn",
    "abstract": "chiều 13/7 , ôtô bmw bất_ngờ lao sang hướng ngược_lại , húc văng hai xe_máy và ba_gác khiến ba người bị_thương , đường kẹt cứng trong giờ cao_điểm .",
    "article": [
        "ôtô bmw húc văng 3 xe ở hướng ngược_lại .",
        "17h , ôtô bmw 325i do người đàn_ông chạy trên đường phan_huy_ích , hướng từ quận tân_bình về gò_vấp , tp hcm .",
        "đang chạy , ôtô bất_ngờ lao sang hướng ngược_lại , húc văng xe ba_gác và hai xe_máy lên vỉa_hè .",
        "tai_nạn khiến cụ bà 72 tuổi được người cháu trai chở đi thăm người_thân bệnh bị chấn_thương nặng ở chân .",
        "nam thanh_niên đi xe_máy và người đàn_ông chạy xe ba_gác chỉ bị trầy_xước nhẹ .",
        "các xe bị nạn hư_hỏng , trong đó chiếc bmw bị móp đầu .",
        "sau tai_nạn , tài_xế ôtô đã rời khỏi hiện_trường .",
        "đường phan_huy_ích bị ừn ứ trong giờ cao_điểm .",
        "lực_lượng chức_năng địa_phương đến phân_luồng giao_thông , phối_hợp đội xử_lý tai_nạn quận tân_bình làm rõ nguyên_nhân vụ tai_nạn .",
        "hải_hiếu"
    ],
    "image": [
        "ôtô bmw húc văng 3 xe ở hướng ngược_lại ."
    ],
    "label": [
        2,
        7,
        1
    ]
}