{
    "title": "nổ lớn trước nhà giám_đốc doanh_nghiệp vận_tải",
    "abstract": "nghe tiếng nổ lớn , hàng_xóm chạy đến thì thấy chủ doanh_nghiệp vận_tải ở phú_yên gục trước nhà , toàn_thân nám đen .",
    "article": [
        "rạng sáng 30/6 , tiếng nổ lớn phát ra trước sân_nhà trên đường mai_xuân_thưởng , tp tuy_hoà .",
        "mọi người hốt_hoảng chạy đến , phát_hiện ông đặng_đức_hối ( 53 tuổi ) bị_thương nhiều chỗ , gục trên nền bêtông .",
        "xung_quanh có nhiều mảnh vỡ và có bịch nhựa màu đen .",
        "\" ông hối lái xe_tải được thời_gian thì mở công_ty chuyên về vận_tải .",
        "ông ấy sống khá hiền , được mọi người xung_quanh quý_mến \" , người_dân nói .",
        "bệnh_viện đa_khoa phú_yên cho_hay , ông hối nhập_viện trong tình_trạng toàn_thân nám đen , mắt bị_thương , gãy ngón chân phải .",
        "\" bệnh_nhân bị nhiều mảnh vỡ ghim vào , nghi do mìn \" , bác_sĩ nói .",
        "cảnh_sát khám_nghiệm hiện_trường .",
        "cảnh_sát khám_nghiệm , điều_tra nguyên_nhân .",
        "nguyên_dương"
    ],
    "image": [
        "cảnh_sát khám_nghiệm hiện_trường ."
    ],
    "label": [
        0,
        5,
        1
    ]
}