{
    "title": "mưa_đá to bằng ngón tay xuất_hiện ở miền tây",
    "abstract": "mưa_đá kéo_dài khoảng một giờ kèm lốc xoáy làm 20 căn nhà_trọ ở long_an bị tốc mái .",
    "article": [
        "người_dân nhặt các viên đá từ cơn mưa .",
        "chiều 2/5 , trận mưa_đá xảy ra tại địa_bàn xã đức_hoà_hạ ( huyện đức_hoà , tỉnh long_an ) .",
        "hạt đá to bằng đầu ngón tay cái , kéo_dài trong khoảng một giờ .",
        "nhiều người_dân hiếu_kỳ dùng điện_thoại ghi lại cảnh các viên đá rơi .",
        "mưa cũng kèm theo lốc xoáy khiến mái tôn của 20 phòng trọ bị cuốn đi hàng chục mét , treo vắt_vẻo trên dây_điện .",
        "giông lốc cũng làm gãy một_số trụ điện khiến nhiều người đi đường hốt_hoảng tìm chỗ trú .",
        "theo ông hồ_thanh_liêm , chủ_tịch xã đức_hoà_hạ , khoảng 20 năm địa_phương chưa thấy có mưa_đá xuất_hiện .",
        "\" chúng_tôi đang thống_kê và khắc_phục hậu_quả do lốc xoáy , vẫn chưa ghi_nhận thiệt_hại về hoa_màu và người \" , ông liêm nói .",
        "cuối tuần trước , nhiều tỉnh_thành ở nam_bộ đã đón mưa \" giải_nhiệt \" sau thời_gian nắng gay_gắt .",
        "lưu_lượng mưa ghi_nhận đến 89 mm ở bình_phước , 86 mm ở bình_dương còn cà_mau là 36 mm .",
        "theo đài_khí_tượng thuỷ_văn khu_vực nam_bộ , mưa giông đang có xu_hướng gia_tăng vào chiều_tối kèm nguy_cơ xảy ra lốc , sét , mưa_đá và gió giật mạnh .",
        "đây là thời_tiết đặc_trưng của giai_đoạn chuyển mùa mưa .",
        "hoàng_nam"
    ],
    "image": [
        "người_dân nhặt các viên đá từ cơn mưa .",
        "video : phạm_tâm .",
        "mái tôn của 20 phòng trọ bị lốc xoáy cuốn đi hàng chục mét ."
    ],
    "label": [
        4,
        2,
        1
    ]
}