{
    "title": "nga sẵn_sàng bán s -400 cho mỹ",
    "abstract": "tập_đoàn rostec của nga tuyên_bố sẵn_sàng bán hệ_thống phòng_không s -400 cho mọi quốc_gia muốn bảo_vệ không_phận của họ , bao_gồm cả mỹ .",
    "article": [
        "một tổ_hợp s -400 triumf của nga .",
        "\" s -400 không phải hệ_thống tấn_công .",
        "nó là hệ_thống phòng_thủ .",
        "chúng_tôi có_thể bán cho mỹ nếu họ muốn \" , sergei_chemezov , đứng đầu tập_đoàn quốc_gia nga_rostec , trả_lời khi được hỏi lý_do nga bán s -400 cho thổ_nhĩ_kỳ trong bài phỏng_vấn đăng trên washington_post ngày 10/2 .",
        "nga cuối năm 2017 chấp_thuận bán hệ_thống tên_lửa phòng_không s -400 cho thổ_nhĩ_kỳ .",
        "ankara sẽ trở_thành thành_viên nato đầu_tiên tích_hợp công_nghệ của nga vào hệ_thống phòng_thủ bắc_đại_tây_dương khi hợp_đồng hoàn_tất .",
        "s -400 , do cục thiết_kế trung_ương almaz phát_triển , được đưa vào biên_chế quân_đội nga từ năm 2007 .",
        "hệ_thống có_thể đánh chặn mục_tiêu từ khoảng_cách 40 km đến 400 km .",
        "s -400 còn được cho là một trong những yếu_tố quan_trọng giúp chiến_dịch diệt nhà_nước hồi_giáo ( is ) ở syria của nga thành_công .",
        "almaz đang phát_triển hệ_thống s -500 .",
        "trong thời_gian này , các đơn hàng s -400 tăng mạnh .",
        "ngoài trung_quốc , thổ_nhĩ_kỳ , nhiều quốc_gia khác như ấn_độ , qatar , arab_saudi đang đàm_phán với nga để mua s -400 .",
        "theo rt , nhu_cầu mua s -400 tăng cao một phần do dòng hệ_thống phòng_thủ này có độ tin_cậy cao .",
        "s -200 , do almaz phát_triển từ thập_niên 1960 , vẫn nằm trong biên_chế quân_đội nhiều nước .",
        "\" khi tình_hình chính_trị thế_giới căng_thẳng , mọi quốc_gia đều tìm cách đảm_bảo an_ninh , an_toàn không_phận \" , chemezov nói .",
        "\" nhiều nước muốn mua hệ_thống phòng_thủ .",
        "chúng_tôi có nhiều đơn hàng .",
        "tất_nhiên là chúng_tôi có cạnh_tranh với mỹ và hệ_thống của chúng_tôi tốt hơn \" .",
        "đối_thủ trực_tiếp của s -400 là hệ_thống phòng_thủ tên_lửa mỹ_patriot .",
        "s -400 có_thể phát_hiện mục_tiêu từ khoảng_cách 600 km , hạ mục_tiêu từ khoảng_cách 400 km .",
        "hai thông_số trên đối_với patriot là 180 km và 130 km .",
        "cả hai đều có khoảng_cách tối_thiểu đánh chặn mục_tiêu , lần_lượt là 2 km và 10 km .",
        "s -400 và patriot có_thể đánh chặn mục_tiêu có tốc_độ tối_đa 17.280 km/h và 7.920 km/h .",
        "hai hệ_thống có tốc_độ ứng_phó tương_đương nhau , chưa đến 10 giây , nhưng s -400 dễ triển_khai hơn , từ chế_độ di_chuyển sáng chiến_đấu chỉ trong 5 phút .",
        "patriot cần tới 25 phút .",
        "dựa vào những thông_tin trên , chemezov đề_xuất mỹ có_thể mua s -400 để bảo_vệ không_phận .",
        "\" chuyện này không có vấn_đề gì , theo quan_điểm chiến_lược và an_ninh \" , ông chemezov nói .",
        "\" ngược_lại , một quốc_gia sẽ cảm_thấy an_toàn hơn nếu có_thể bảo_vệ tốt không_phận .",
        "những bên có ý_định tấn_công phải suy_nghĩ kỹ \" .",
        "như_tâm"
    ],
    "image": [
        "một tổ_hợp s -400 triumf của nga ."
    ],
    "label": [
        4,
        27
    ]
}