{
    "title": "cặp song_sinh có mái_tóc không_thể chải như bờm sư_tử",
    "abstract": "hai bé gái sinh_đôi người anh_agnetha và anja_norendal có mái_tóc như bờm sư_tử vì mắc hội_chứng tóc không_thể chải .",
    "article": [
        "agnetha và anja_norendal .",
        "bé agnetha và anja_norendal , 9 tuổi , ở cockermouth , cumbria , anh luôn khiến người đi đường hiếu_kỳ , brief_report ngày 25/8 đưa tin .",
        "bà angela , 52 tuổi , mẹ của cặp song_sinh nhận ra sự khác_thường ngay khi hai con bắt_đầu mọc tóc với những sợi tóc cứng , xoăn , không_thể chải vào nếp .",
        "một bác_sĩ từng đoán hai em mắc hội_chứng tóc không_thể chải ( uhs ) , xảy ra do đột_biến gene .",
        "dù chưa đưa hai con đi kiểm_tra chính_thức , gia_đình tin chắc hai bé gái mắc uhs .",
        "\" tôi không biết có_thể là nguyên_nhân nào khác .",
        "hội_chứng này hình_như cũng tạo nên màu tóc vàng sáng xuất_hiện ở những đứa trẻ cùng mắc hội_chứng này \" , bà angela cho_biết .",
        "agnetha và anja chỉ mới ba lần cắt tóc trong đời với độ dài khoảng 6 cm do tóc mọc rất chậm .",
        "bà angela chỉ có_thể gội đầu cho hai con một lần mỗi tuần để tránh làm rối tóc .",
        "\" chúng_tôi hầu_như không dùng dầu_gội đầu vì dầu_gội làm tóc xoăn cứng thêm .",
        "nhưng mỗi tuần chúng_tôi dùng hết một chai dầu xả \" , bà nói .",
        "mái_tóc bờm sư_tử khiến người lạ luôn muốn xin chụp ảnh cùng hai cô_bé .",
        "\" bọn trẻ ở trường cũng thích mái_tóc này \" , mẹ của cặp sinh_đôi kể .",
        "\" tôi rất muốn biết liệu có cặp song_sinh nào khác có mái_tóc như_vậy hay không . \"",
        "nhờ internet , gia_đình có_thể liên_lạc với những người có con mắc cùng triệu_chứng .",
        "trên thế_giới có khoảng 100 trẻ_em mắc uhs .",
        "\" thật tốt khi có_thể nói_chuyện với những người hiểu chuyện .",
        "nhưng tôi không cho rằng hội_chứng này ảnh_hưởng lớn tới cuộc_sống của các con \" , angela nói .",
        "vũ_phong"
    ],
    "image": [
        "agnetha và anja_norendal ."
    ],
    "label": [
        3,
        0
    ]
}