{
    "title": "giá vàng hôm_nay 16/4 : vàng 9999 , vàng sjc , vàng_tây đồng_loạt lao dốc",
    "abstract": "giá vàng hôm_nay 16/4 ghi_nhận giảm trên tất_cả các bình_diện . từ vàng 9999 , vàng sjc tới vàng_tây , tại các nhà vàng đều giảm . đây được xem là diễn_biến mạnh_mẽ , đồng_bộ đầu_tiên của giá vàng sau nhiều ngày trồi_sụt thất_thường .",
    "article": [
        "giá vàng trong nước hôm_nay 16/4",
        "giá vàng sjc hôm_nay 16/4 của tập_đoàn doji tại thị_trường hà_nội là 36,33 triệu đồng / lượng ( mua vào ) và 36,43 triệu đồng / lượng ( bán ra ) , giảm_giá 50.000 đồng / lượng so với giá phiên mở_cửa sáng hôm trước .",
        "trong khi đó , tập_đoàn phú_quý niêm_yết giá vàng sjc mua vào 36,35 triệu đồng / lượng , bán ra 36,45 triệu đồng / lượng , giảm_giá 30.000 đồng / lượng so với phiên giao_dịch sáng 15/4 .",
        "giá vàng sjc hôm_nay 16/4 của công_ty tập_đoàn vàng_bạc đá_quý sài_gòn sjc niêm_yết mức 36,31 triệu đồng / lượng ( mua vào ) , 36,46 triệu đồng / lượng ( bán ra ) , giảm_giá 30.000 đồng / lượng cả hai chiều so với ngày hôm_qua .",
        "trong khi đó , giá vàng 9999 của phú_quý hôm_nay 16/4 chiều mua vào với giá 36,30 triệu đồng / lượng , bán ra với giá 36,70 triệu đồng / lượng .",
        "giá vàng 9999 hôm_nay 16/4 của công_ty tập_đoàn vàng_bạc đá_quý sài_gòn tại thị_trường tp. hcm là 36,30 triệu đồng / lượng mua vào , bán ra 36,70 triệu đồng / lượng , giảm 70.000 đồng / lượng .",
        "giá vàng ta hôm_nay 16/4 , giá mua vào 3.631.000 đồng một chỉ , bán ra 3.671.000 đồng một chỉ , giảm 60.000 đồng một chỉ cả hai chiều .",
        "giá vàng_tây hôm_nay 16/4 tăng nhẹ .",
        "giá vàng 24k mua vào 3.539.900 đồng một chỉ , bán ra 3.609.900 đồng một chỉ .",
        "trong khi đó , giá vàng_tây 18k mua vào 2.609.800 đồng một chỉ , bán ra 2.749.800 đồng một chỉ .",
        "như_vậy , sau rất nhiều ngay trồi lên trụt xuống , giá vàng hôm_nay ghi_nhận giảm khá mạnh trên tất_cả các lạo vàng 9999 , vàng sjc , vàng_tây , vàng ta .",
        "giá vàng thế_giới hôm_nay 16/4",
        "tới đầu giờ sáng 16/4 ( giờ việt_nam ) , giá vàng thế_giới giao ngay đứng ở mức 1.283 usd / ounce .",
        "giá vàng thế_giới lao dốc sau khi thủng sâu dưới ngưỡng hỗ_trợ quan_trọng .",
        "áp_lực bán theo phân_tích kỹ_thuật và tâm_lý ưa_thích các loại tài_sản rủi_ro quay trở_lại khiến sức cầu đối_với vàng tụt giảm nghiêm_trọng .",
        "bất_chấp việc đồng usd tụt giảm sâu xuống dưới ngưỡng 97 điểm , giá vàng vẫn giảm mạnh .",
        "liên_tiếp các tín_hiệu tích_cực đến với các nền kinh_tế lớn trên thế_giới , đặc_biệt là trung_quốc đã làm giảm bớt nỗi_lo về khả_năng nền kinh_tế toàn_cầu giảm_tốc .",
        "số_liệu từ tổng_cục hải_quan trung_quốc mới công_bố cho thấy xuất_khẩu của nước này trong quý i diễn_biến tích_cực .",
        "trong quý i , xuất_siêu của trung_quốc lên tới 79 tỷ usd , tăng hơn 75 % so với cùng kỳ năm trước .",
        "nền kinh_tế trung_quốc phát_triển khá tốt giúp tỷ_giá đồng_nhân_dân_tệ tương_đối ổn_định .",
        "trong khi đó , các doanh_nghiệp mỹ cũng bất_ngờ công_bố lợi_nhuận cao một_cách ngạc_nhiên .",
        "giá vàng trong nước chốt phiên ngày 13/4 ( trước kỳ nghỉ lễ ) của doji với giá vàng sjc là 36,38 triệu đồng / lượng ( mua vào ) và 36,48 triệu đồng / lượng ( bán ra ) .",
        "giá vàng sjc của công_ty vàng_bạc đá_quý sài_gòn chiều mua vào 36,34 triệu đồng / lượng và 36,51 triệu đồng / lượng chiều bán ra ."
    ],
    "image": [
        "giá vàng hôm_nay 16/4 : vàng 9999 , vàng sjc , vàng_tây đồng_loạt lao dốc"
    ],
    "label": [
        10,
        11
    ]
}