{
    "title": "bắt nghi can giết nữ chủ tiệm cầm đồ",
    "abstract": "sáng 4-5 , nguồn tin từ công_an tỉnh bình thuận cho biết các đơn vị nghiệp vụ đã bắt được nghi_can gây ra cái chết của bà chủ tiệm cầm đồ thu_trang ở xã vĩnh hảo , huyện tuy_phong .",
    "article": [
        "theo đó , nghi_can được xác_định là nguyễn văn tuấn , 28 tuổi , quê tỉnh quảng bình .",
        "nạn nhân là bà trương phạm thu_trang , 43 tuổi , chủ tiệm cầm đồ thu_trang .",
        "thời điểm công_an bắt giữ , tuấn đang lẩn trốn tại một căn nhà hoang ở xã vĩnh tân , huyện tuy_phong , trên người còn dính nhiều vết máu .",
        "khám xét nhanh , công_an phát hiện tuấn còn mang một điện thoại có hình bà trang và một số tiền .",
        "trước đó , trưa 3-5 , con gái bà trang đi học về thấy một nam thanh_niên lạ mặt chạy xe từ trong nhà ra .",
        "khi vào đến bên trong , con nạn nhân phát hiện bà trang nằm bất động với nhiều vết máu .",
        "do vết thương quá nặng nên bà trang đã tử_vong ."
    ],
    "image": [
        "hiện trường vụ án mạng - ảnh : ctv .",
        "người_dân hiếu_kỳ vây kín hiện trường vụ án mạng - ảnh : ctv"
    ],
    "label": [
        1,
        2
    ]
}