{
    "title": "ôtô cháy rụi sau khi lùi qua đống lửa",
    "abstract": "chiếc ôtô 4 chỗ đậu trên con phố ở thanh_hoá cháy trơ khung sau khoảng 20 phút .",
    "article": [
        "khoảng 11h ngày 23/6 , chiếc ôtô bốn chỗ biển số hà_nội đang đỗ trên phố lương_đình_của , phường đông_thọ , thành_phố thanh_hoá thì bất_ngờ bốc cháy dữ_dội .",
        "do thời_tiết nắng_nóng , ngọn lửa nhanh_chóng bao_trùm thân xe .",
        "hiện_trường vụ cháy .",
        "sau khoảng 20 phút , đám cháy được khống_chế song chiếc xe bị thiêu rụi hoàn_toàn .",
        "cảnh_sát nghi_ngờ tài_xế đã bất_cẩn lùi xe qua đống rác đang cháy khiến than nóng bám vào gầm xe gây cháy .",
        "chiếc xe bị thiêu rụi sau khoảng 20 phút .",
        "chiếc xe bị cháy có giá_trị trên 600 triệu đồng ."
    ],
    "image": [
        "chiếc xe bị thiêu rụi sau khoảng 20 phút ."
    ],
    "label": [
        5,
        0
    ]
}