{
    "title": "taxi tông gãy trụ đèn_cao_áp , ba người nhập_viện",
    "abstract": "chở khách vào huế , xe taxi bất_ngờ tông vào con lươn giữa đường khiến đầu xe nát bấy , nhiều người bị_thương .",
    "article": [
        "khoảng 12h30 , xe của hãng taxi thành_công chở bốn hành_khách theo hướng từ bến_xe phía bắc vào thành_phố huế .",
        "khi đến đường lê_duẩn ( phường phú_thuận , tp huế ) chiếc xe húc thẳng vào trụ điện cao_áp nằm giữa con lươn .",
        "chiếc xe taxi bị hư_hỏng nặng phần đầu .",
        "sau cú va_chạm mạnh , đầu xe taxi nát vụn , xăng_dầu chảy lênh_láng mặt_đường , trụ đèn cao khoảng 5m gãy xuống_đường .",
        "người_dân sống hai bên đường lê_duẩn đã đưa tài_xế tên trung và hai hành_khách đi cấp_cứu tại bệnh_viện trung_ương huế .",
        "hai người khác bị_thương nhẹ .",
        "nguyên_nhân tai_nạn đang được điều_tra ."
    ],
    "image": [
        "chiếc xe taxi bị hư_hỏng nặng phần đầu ."
    ],
    "label": [
        1,
        2
    ]
}